COPYING.txt
MANIFEST.in
README.md
setup.cfg
setup.py
morpy/__init__.py
morpy/cmorton.c
morpy/cmorton.pyx
morpy/morton.py
morpy/test_cmorton.py
morpy.egg-info/PKG-INFO
morpy.egg-info/SOURCES.txt
morpy.egg-info/dependency_links.txt
morpy.egg-info/requires.txt
morpy.egg-info/top_level.txt