Metadata-Version: 1.1
Name: morpy
Version: 0.1.4
Summary: Morton Curve Library
Home-page: UNKNOWN
Author: Samuel Skillman <samskillman@gmail.com>
Author-email: UNKNOWN
License: MIT
Keywords: space filling curve,morton
Platform: UNKNOWN
Classifier: Programming Language :: Python
Classifier: Topic :: Software Development :: Libraries :: Python Modules
